diycrate/__init__.py
diycrate/cache_utils.py
diycrate/diycrate_app.py
diycrate/file_operations.py
diycrate/gui.py
diycrate/item_queue_io.py
diycrate/iter_utils.py
diycrate/log_utils.py
diycrate/logging_config.py
diycrate/long_poll_processing.py
diycrate/oauth_utils.py
diycrate/path_utils.py
diycrate/server_app.py
diycrate/utils.py
diycrate-0.2.11.3.dist-info/LICENSE
diycrate-0.2.11.3.dist-info/METADATA
diycrate-0.2.11.3.dist-info/WHEEL
diycrate-0.2.11.3.dist-info/entry_points.txt
diycrate-0.2.11.3.dist-info/top_level.txt
diycrate-0.2.11.3.dist-info/RECORD
