Metadata-Version: 2.1
Name: diycrate
Version: 0.2.11.3
Summary: box.com for linux -- unofficial, based on python SDK
Home-page: https://github.com/jheld/diycrate
Author-email: Jason Held <jasonsheld@gmail.com>
Project-URL: Source, https://github.com/jheld/diycrate/
Project-URL: Issues, https://github.com/jheld/diycrate/issues
Keywords: cloud,storage,box.com,sdk,linux,box
Classifier: Development Status :: 3 - Alpha
Classifier: Topic :: Utilities
Classifier: License :: OSI Approved :: MIT License
Classifier: Intended Audience :: Developers
Classifier: Operating System :: POSIX :: Linux
Classifier: Environment :: Console
Classifier: Environment :: Web Environment
Classifier: Intended Audience :: End Users/Desktop
Classifier: Programming Language :: Python :: 3
Classifier: Programming Language :: Python :: 3.8
Classifier: Programming Language :: Python :: 3.9
Classifier: Programming Language :: Python :: 3.10
Classifier: Programming Language :: Python :: 3 :: Only
Requires-Python: <4,>=3.6
License-File: LICENSE
Requires-Dist: fastapi ~=0.104.1
Requires-Dist: uvicorn ~=0.24.0
Requires-Dist: python-multipart ==0.0.6
Requires-Dist: boxsdk <3.0,>=2.0
Requires-Dist: pyinotify ==0.9.6
Requires-Dist: redis ~=3.3.0
Requires-Dist: httpx ==0.22.0
Requires-Dist: pyopenssl >=16.0.0
Requires-Dist: python-dateutil
Requires-Dist: certbot ==1.12.0
Requires-Dist: Send2Trash ==1.8.0
Requires-Dist: urllib3 ==1.26.15
Provides-Extra: ci
Requires-Dist: python-digitalocean ; extra == 'ci'
Provides-Extra: dev
Requires-Dist: ipython ; extra == 'dev'
Requires-Dist: check-manifest ; extra == 'dev'
Requires-Dist: black ; extra == 'dev'
Requires-Dist: flake8 ; extra == 'dev'
Requires-Dist: pre-commit ; extra == 'dev'
Requires-Dist: mypy ; extra == 'dev'
Provides-Extra: systemd
Requires-Dist: systemd-python ; extra == 'systemd'
Provides-Extra: test
Requires-Dist: tox ; extra == 'test'
Requires-Dist: check-manifest ; extra == 'test'
